CHANGELOG
LICENSE
README.org
nacf/__init__.py
nacf/models.py
nacf/tools.py
nacf/types.py
poetry.lock
nacf-1.0.3.dist-info/LICENSE
nacf-1.0.3.dist-info/WHEEL
nacf-1.0.3.dist-info/METADATA
nacf-1.0.3.dist-info/RECORD
