Metadata-Version: 2.1
Name: nacf
Version: 1.0.3
Summary: Nasy Crawler Framework -- Never had such a pure crawler.
Home-page: https://github.com/nasyxx/nacf
License: LGPL-3.0+
Keywords: crawler
Author: Nasy
Author-email: nasyxx+nacf@gmail.com
Requires-Python: >=3.6,<4.0
Classifier: License :: OSI Approved :: GNU Lesser General Public License v3 or later (LGPLv3+)
Classifier: Programming Language :: Python :: 3
Classifier: Programming Language :: Python :: 3.6
Classifier: Programming Language :: Python :: 3.7
Classifier: Topic :: Software Development :: Libraries :: Application Frameworks
Classifier: Topic :: Utilities
Requires-Dist: nalude (>=0.3)
Requires-Dist: requests_html (<1.0.0)
Project-URL: Repository, https://github.com/nasyxx/nacf
